CREDITS
LICENSE
MANIFEST.in
README.rst
build_inplace
setup.cfg
setup.py
docs/Makefile
docs/conf.py
docs/index.rst
docs/make.bat
docs/why.rst
fibers/__init__.py
fibers/_pyfibers.py
fibers_ddtest.egg-info/PKG-INFO
fibers_ddtest.egg-info/SOURCES.txt
fibers_ddtest.egg-info/dependency_links.txt
fibers_ddtest.egg-info/top_level.txt
src/fibers.c
src/fibers.h
src/slp_platformselect.h
src/stacklet.c
src/stacklet.h
src/switch_arm_gcc.h
src/switch_mips64_gcc.h
src/switch_ppc64_gcc.h
src/switch_s390x_gcc.h
src/switch_x64_msvc.asm
src/switch_x64_msvc.h
src/switch_x86_64_gcc.h
src/switch_x86_gcc.h
src/switch_x86_msvc.asm
src/switch_x86_msvc.h
tests/test_fibers.py
tests/test_gc.py
tests/test_generator.py
tests/test_generator_nested.py
tests/test_leaks.py
tests/test_throw.py
tests/test_weakref.py